pydxl/__init__.py
pydxl/dynamixel.py
pydxl/exceptions.py
pydxl/mx28.py
pydxl/packet.py
pydxl/port_handler.py
pydxl/protocol1.py
pydxl/register.py
pydxl/seriallink.py
pydxl-2019.3.19.dist-info/AUTHORS.rst
pydxl-2019.3.19.dist-info/LICENSE
pydxl-2019.3.19.dist-info/METADATA
pydxl-2019.3.19.dist-info/WHEEL
pydxl-2019.3.19.dist-info/top_level.txt
pydxl-2019.3.19.dist-info/RECORD
