Metadata-Version: 2.1
Name: pydxl
Version: 2019.3.19
Summary: Python package to use Dynamixel servos through a serial interface.
Home-page: https://github.com/vpoulailleau/pydxl
Author: Vincent Poulailleau
Author-email: vpoulailleau@gmail.com
License: BSD license
Keywords: pydxl
Platform: UNKNOWN
Classifier: Development Status :: 2 - Pre-Alpha
Classifier: Intended Audience :: Developers
Classifier: License :: OSI Approved :: BSD License
Classifier: Natural Language :: English
Classifier: Programming Language :: Python :: 3
Classifier: Programming Language :: Python :: 3.6
Classifier: Programming Language :: Python :: 3.7
Requires-Dist: pyserial (==3.4)
